valthon/__init__.py
valthon/cli.py
valthon/importing.py
valthon/logger.py
valthon/parser.py
valthon/translator.py
valthon-1.1.2.dist-info/METADATA
valthon-1.1.2.dist-info/WHEEL
valthon-1.1.2.dist-info/entry_points.txt
valthon-1.1.2.dist-info/licenses/LICENSE
valthon-1.1.2.dist-info/RECORD
