Metadata-Version: 2.4
Name: valthon
Version: 1.1.2
Summary: Python with Valorant
Project-URL: Homepage, https://github.com/harshal6927/valthon
Project-URL: Website, https://harshallaheri.me/
Author-email: Harshal Laheri <harshal@harshallaheri.me>
License: MIT
License-File: LICENSE
Requires-Python: >=3.8
Requires-Dist: click==8.1.8
